{"sections":{"main":{"type":"main-page","disabled":true,"settings":{"padding_top":60,"padding_bottom":60}},"custom_multicolumn_gbGEYM":{"type":"custom-multicolumn","blocks":{"column_W7gPf4":{"type":"column","settings":{"image":"shopify:\/\/shop_images\/1_b42022be-3719-4459-8c53-c7b91df22159.png","title":"","title_size":"h2","text":"","link_label":"","link":""}},"column_Mgjdpw":{"type":"column","settings":{"image":"shopify:\/\/shop_images\/2_f68a5106-862f-4158-b48e-95611980bc56.png","title":"","title_size":"h2","text":"","link_label":"","link":""}}},"block_order":["column_W7gPf4","column_Mgjdpw"],"settings":{"title":"Our menu","heading_size":"h1","text":"","image_width":"full","image_ratio":"adapt","columns_desktop":2,"column_alignment":"center","background_style":"none","button_label":"","button_link":"","color_scheme":"","columns_mobile":"1","swipe_on_mobile":false,"padding_top":60,"padding_bottom":60}}},"order":["main","custom_multicolumn_gbGEYM"]}